<?xml version="1.0" encoding="UTF-8" standalone="yes"?>
<dgm:dataModel xmlns:dgm="http://schemas.openxmlformats.org/drawingml/2006/diagram" xmlns:a="http://schemas.openxmlformats.org/drawingml/2006/main"><dgm:ptLst><dgm:pt modelId="{6B1B2AEF-22F4-AC48-8A93-AB0CB308BE29}" type="doc"><dgm:prSet loTypeId="urn:microsoft.com/office/officeart/2005/8/layout/hChevron3" loCatId="process" qsTypeId="urn:microsoft.com/office/officeart/2005/8/quickstyle/simple4" qsCatId="simple" csTypeId="urn:microsoft.com/office/officeart/2005/8/colors/accent1_2" csCatId="accent1" phldr="1"/><dgm:spPr/></dgm:pt><dgm:pt modelId="{3AD67424-697F-3C4E-AF06-C23AA73C6735}"><dgm:prSet phldrT="[Text]" phldr="1" custT="1"/><dgm:spPr><a:noFill/><a:ln><a:solidFill><a:schemeClr val="tx1"/></a:solidFill></a:ln><a:effectLst/></dgm:spPr><dgm:t><a:bodyPr/><a:lstStyle/><a:p><a:endParaRPr lang="en-US" sz="1200" dirty="0"><a:solidFill><a:schemeClr val="tx1"/></a:solidFill></a:endParaRPr></a:p></dgm:t></dgm:pt><dgm:pt modelId="{94A1EA08-330E-1C4F-A5F6-B6D027255A25}" type="parTrans" cxnId="{270A698C-79CC-BA4F-BA71-C01DD8069CDB}"><dgm:prSet/><dgm:spPr/><dgm:t><a:bodyPr/><a:lstStyle/><a:p><a:endParaRPr lang="en-US"/></a:p></dgm:t></dgm:pt><dgm:pt modelId="{B660B384-A234-FF4B-953C-B968334A83B1}" type="sibTrans" cxnId="{270A698C-79CC-BA4F-BA71-C01DD8069CDB}"><dgm:prSet/><dgm:spPr/><dgm:t><a:bodyPr/><a:lstStyle/><a:p><a:endParaRPr lang="en-US"/></a:p></dgm:t></dgm:pt><dgm:pt modelId="{4AEC236B-9451-FE45-8C5E-68D1AA342D88}"><dgm:prSet phldrT="[Text]" phldr="1" custT="1"/><dgm:spPr><a:noFill/><a:ln><a:solidFill><a:schemeClr val="tx1"/></a:solidFill></a:ln><a:effectLst/></dgm:spPr><dgm:t><a:bodyPr/><a:lstStyle/><a:p><a:endParaRPr lang="en-US" sz="1200"><a:solidFill><a:schemeClr val="tx1"/></a:solidFill></a:endParaRPr></a:p></dgm:t></dgm:pt><dgm:pt modelId="{AF267801-2239-F94A-B583-C7FB27956B7F}" type="parTrans" cxnId="{735FF7A0-A1B2-2B48-B7AA-8B3F6CA7AA2B}"><dgm:prSet/><dgm:spPr/><dgm:t><a:bodyPr/><a:lstStyle/><a:p><a:endParaRPr lang="en-US"/></a:p></dgm:t></dgm:pt><dgm:pt modelId="{41AD188D-17A6-8643-88D4-9938D158A470}" type="sibTrans" cxnId="{735FF7A0-A1B2-2B48-B7AA-8B3F6CA7AA2B}"><dgm:prSet/><dgm:spPr/><dgm:t><a:bodyPr/><a:lstStyle/><a:p><a:endParaRPr lang="en-US"/></a:p></dgm:t></dgm:pt><dgm:pt modelId="{15C0F98F-A1BA-E545-B3AC-C70E2FD60E30}"><dgm:prSet phldrT="[Text]" phldr="1" custT="1"/><dgm:spPr><a:noFill/><a:ln><a:solidFill><a:schemeClr val="tx1"/></a:solidFill></a:ln><a:effectLst/></dgm:spPr><dgm:t><a:bodyPr/><a:lstStyle/><a:p><a:endParaRPr lang="en-US" sz="1200" dirty="0"><a:solidFill><a:schemeClr val="tx1"/></a:solidFill></a:endParaRPr></a:p></dgm:t></dgm:pt><dgm:pt modelId="{F34FC41A-5477-8F43-BFA0-1C6486C8F3D7}" type="parTrans" cxnId="{E57464E3-C512-A942-9482-554D96FBAF65}"><dgm:prSet/><dgm:spPr/><dgm:t><a:bodyPr/><a:lstStyle/><a:p><a:endParaRPr lang="en-US"/></a:p></dgm:t></dgm:pt><dgm:pt modelId="{41625998-06A4-3D44-A4C7-DAB70713663D}" type="sibTrans" cxnId="{E57464E3-C512-A942-9482-554D96FBAF65}"><dgm:prSet/><dgm:spPr/><dgm:t><a:bodyPr/><a:lstStyle/><a:p><a:endParaRPr lang="en-US"/></a:p></dgm:t></dgm:pt><dgm:pt modelId="{7EC28C01-B1CB-E740-88E0-8B1B947A90BE}"><dgm:prSet phldrT="[Text]" custT="1"/><dgm:spPr><a:noFill/><a:ln><a:solidFill><a:schemeClr val="tx1"/></a:solidFill></a:ln><a:effectLst/></dgm:spPr><dgm:t><a:bodyPr/><a:lstStyle/><a:p><a:endParaRPr lang="en-US" sz="1200" dirty="0"><a:solidFill><a:schemeClr val="tx1"/></a:solidFill></a:endParaRPr></a:p></dgm:t></dgm:pt><dgm:pt modelId="{536E123D-41B8-5943-A0C0-CBF91265352D}" type="parTrans" cxnId="{43917434-DF30-B848-BEE2-21CD9A51C9F7}"><dgm:prSet/><dgm:spPr/><dgm:t><a:bodyPr/><a:lstStyle/><a:p><a:endParaRPr lang="en-US"/></a:p></dgm:t></dgm:pt><dgm:pt modelId="{35F9A163-1378-3344-8B65-356AB8D3CFB8}" type="sibTrans" cxnId="{43917434-DF30-B848-BEE2-21CD9A51C9F7}"><dgm:prSet/><dgm:spPr/><dgm:t><a:bodyPr/><a:lstStyle/><a:p><a:endParaRPr lang="en-US"/></a:p></dgm:t></dgm:pt><dgm:pt modelId="{7B63C8FB-3594-9F4C-AA26-6E34EF478988}"><dgm:prSet phldrT="[Text]" custT="1"/><dgm:spPr><a:noFill/><a:ln><a:solidFill><a:schemeClr val="tx1"/></a:solidFill></a:ln><a:effectLst/></dgm:spPr><dgm:t><a:bodyPr/><a:lstStyle/><a:p><a:endParaRPr lang="en-US" sz="1200" dirty="0"><a:solidFill><a:schemeClr val="tx1"/></a:solidFill></a:endParaRPr></a:p></dgm:t></dgm:pt><dgm:pt modelId="{33C868A5-0974-2443-88E7-8E0EE4F8547E}" type="parTrans" cxnId="{0428DC5D-881F-B742-9C29-23BD3B0CC45F}"><dgm:prSet/><dgm:spPr/><dgm:t><a:bodyPr/><a:lstStyle/><a:p><a:endParaRPr lang="en-US"/></a:p></dgm:t></dgm:pt><dgm:pt modelId="{6DCD0E73-6C12-2F49-ABA4-A94461CE8E33}" type="sibTrans" cxnId="{0428DC5D-881F-B742-9C29-23BD3B0CC45F}"><dgm:prSet/><dgm:spPr/><dgm:t><a:bodyPr/><a:lstStyle/><a:p><a:endParaRPr lang="en-US"/></a:p></dgm:t></dgm:pt><dgm:pt modelId="{10F8E38D-B283-824B-BB42-63E45FF74DA9}"><dgm:prSet phldrT="[Text]" custT="1"/><dgm:spPr><a:noFill/><a:ln><a:solidFill><a:schemeClr val="tx1"/></a:solidFill></a:ln><a:effectLst/></dgm:spPr><dgm:t><a:bodyPr/><a:lstStyle/><a:p><a:endParaRPr lang="en-US" sz="1200" dirty="0"><a:solidFill><a:schemeClr val="tx1"/></a:solidFill></a:endParaRPr></a:p></dgm:t></dgm:pt><dgm:pt modelId="{E7105258-4FB8-FC45-B691-A00612A4A218}" type="parTrans" cxnId="{52FC1B0F-0D64-C542-9472-BDD61265C975}"><dgm:prSet/><dgm:spPr/><dgm:t><a:bodyPr/><a:lstStyle/><a:p><a:endParaRPr lang="en-US"/></a:p></dgm:t></dgm:pt><dgm:pt modelId="{8B7335AD-E8E3-B540-A78E-B15B18EA174D}" type="sibTrans" cxnId="{52FC1B0F-0D64-C542-9472-BDD61265C975}"><dgm:prSet/><dgm:spPr/><dgm:t><a:bodyPr/><a:lstStyle/><a:p><a:endParaRPr lang="en-US"/></a:p></dgm:t></dgm:pt><dgm:pt modelId="{29493BC4-8567-DC44-8124-D9A4E206014B}"><dgm:prSet phldrT="[Text]" custT="1"/><dgm:spPr><a:noFill/><a:ln><a:solidFill><a:schemeClr val="tx1"/></a:solidFill></a:ln><a:effectLst/></dgm:spPr><dgm:t><a:bodyPr/><a:lstStyle/><a:p><a:endParaRPr lang="en-US" sz="1200" dirty="0"><a:solidFill><a:schemeClr val="tx1"/></a:solidFill></a:endParaRPr></a:p></dgm:t></dgm:pt><dgm:pt modelId="{750DED83-2DDF-EF4B-9BDA-90028A97299D}" type="parTrans" cxnId="{BEE2664C-9235-C541-802D-E3F7AA7BEF79}"><dgm:prSet/><dgm:spPr/><dgm:t><a:bodyPr/><a:lstStyle/><a:p><a:endParaRPr lang="en-US"/></a:p></dgm:t></dgm:pt><dgm:pt modelId="{F059D63E-6FC1-3D43-B123-5800FD425444}" type="sibTrans" cxnId="{BEE2664C-9235-C541-802D-E3F7AA7BEF79}"><dgm:prSet/><dgm:spPr/><dgm:t><a:bodyPr/><a:lstStyle/><a:p><a:endParaRPr lang="en-US"/></a:p></dgm:t></dgm:pt><dgm:pt modelId="{5E5CA806-1D07-5F45-B976-8288ED4D0D28}" type="pres"><dgm:prSet presAssocID="{6B1B2AEF-22F4-AC48-8A93-AB0CB308BE29}" presName="Name0" presStyleCnt="0"><dgm:presLayoutVars><dgm:dir/><dgm:resizeHandles val="exact"/></dgm:presLayoutVars></dgm:prSet><dgm:spPr/></dgm:pt><dgm:pt modelId="{E52473DA-8085-644E-A894-B9D49D220693}" type="pres"><dgm:prSet presAssocID="{3AD67424-697F-3C4E-AF06-C23AA73C6735}" presName="parTxOnly" presStyleLbl="node1" presStyleIdx="0" presStyleCnt="7"><dgm:presLayoutVars><dgm:bulletEnabled val="1"/></dgm:presLayoutVars></dgm:prSet><dgm:spPr/></dgm:pt><dgm:pt modelId="{293B8D6C-3AE8-FD4D-9E38-D46F2D15017B}" type="pres"><dgm:prSet presAssocID="{B660B384-A234-FF4B-953C-B968334A83B1}" presName="parSpace" presStyleCnt="0"/><dgm:spPr/></dgm:pt><dgm:pt modelId="{9C4DA93F-6182-1C4F-B14A-DE5E65D63BCA}" type="pres"><dgm:prSet presAssocID="{4AEC236B-9451-FE45-8C5E-68D1AA342D88}" presName="parTxOnly" presStyleLbl="node1" presStyleIdx="1" presStyleCnt="7"><dgm:presLayoutVars><dgm:bulletEnabled val="1"/></dgm:presLayoutVars></dgm:prSet><dgm:spPr/></dgm:pt><dgm:pt modelId="{B53EC07B-4AB7-0C47-9190-7F61A4B97119}" type="pres"><dgm:prSet presAssocID="{41AD188D-17A6-8643-88D4-9938D158A470}" presName="parSpace" presStyleCnt="0"/><dgm:spPr/></dgm:pt><dgm:pt modelId="{54E784E2-E136-2242-A4D6-7739730A0D5F}" type="pres"><dgm:prSet presAssocID="{15C0F98F-A1BA-E545-B3AC-C70E2FD60E30}" presName="parTxOnly" presStyleLbl="node1" presStyleIdx="2" presStyleCnt="7"><dgm:presLayoutVars><dgm:bulletEnabled val="1"/></dgm:presLayoutVars></dgm:prSet><dgm:spPr/></dgm:pt><dgm:pt modelId="{EB4F028F-6C69-DC4B-A30F-9B616CB88233}" type="pres"><dgm:prSet presAssocID="{41625998-06A4-3D44-A4C7-DAB70713663D}" presName="parSpace" presStyleCnt="0"/><dgm:spPr/></dgm:pt><dgm:pt modelId="{9E113E60-D12D-7745-BF29-D52C962884CE}" type="pres"><dgm:prSet presAssocID="{7B63C8FB-3594-9F4C-AA26-6E34EF478988}" presName="parTxOnly" presStyleLbl="node1" presStyleIdx="3" presStyleCnt="7"><dgm:presLayoutVars><dgm:bulletEnabled val="1"/></dgm:presLayoutVars></dgm:prSet><dgm:spPr/></dgm:pt><dgm:pt modelId="{5E5369F1-0642-AA42-BCEC-EF0F2E94DA01}" type="pres"><dgm:prSet presAssocID="{6DCD0E73-6C12-2F49-ABA4-A94461CE8E33}" presName="parSpace" presStyleCnt="0"/><dgm:spPr/></dgm:pt><dgm:pt modelId="{7BECD734-A12F-534A-89A0-5868FE57EAFC}" type="pres"><dgm:prSet presAssocID="{10F8E38D-B283-824B-BB42-63E45FF74DA9}" presName="parTxOnly" presStyleLbl="node1" presStyleIdx="4" presStyleCnt="7"><dgm:presLayoutVars><dgm:bulletEnabled val="1"/></dgm:presLayoutVars></dgm:prSet><dgm:spPr/></dgm:pt><dgm:pt modelId="{F1495C49-065A-504A-8C90-355DE9B579D5}" type="pres"><dgm:prSet presAssocID="{8B7335AD-E8E3-B540-A78E-B15B18EA174D}" presName="parSpace" presStyleCnt="0"/><dgm:spPr/></dgm:pt><dgm:pt modelId="{9E51B29C-3BED-9640-B87A-882DE8B574A5}" type="pres"><dgm:prSet presAssocID="{29493BC4-8567-DC44-8124-D9A4E206014B}" presName="parTxOnly" presStyleLbl="node1" presStyleIdx="5" presStyleCnt="7"><dgm:presLayoutVars><dgm:bulletEnabled val="1"/></dgm:presLayoutVars></dgm:prSet><dgm:spPr/></dgm:pt><dgm:pt modelId="{CB802434-164D-2B47-A8E6-CB84BE54A879}" type="pres"><dgm:prSet presAssocID="{F059D63E-6FC1-3D43-B123-5800FD425444}" presName="parSpace" presStyleCnt="0"/><dgm:spPr/></dgm:pt><dgm:pt modelId="{EA6F2962-465F-464A-B531-E0DD672D52E8}" type="pres"><dgm:prSet presAssocID="{7EC28C01-B1CB-E740-88E0-8B1B947A90BE}" presName="parTxOnly" presStyleLbl="node1" presStyleIdx="6" presStyleCnt="7"><dgm:presLayoutVars><dgm:bulletEnabled val="1"/></dgm:presLayoutVars></dgm:prSet><dgm:spPr/></dgm:pt></dgm:ptLst><dgm:cxnLst><dgm:cxn modelId="{52FC1B0F-0D64-C542-9472-BDD61265C975}" srcId="{6B1B2AEF-22F4-AC48-8A93-AB0CB308BE29}" destId="{10F8E38D-B283-824B-BB42-63E45FF74DA9}" srcOrd="4" destOrd="0" parTransId="{E7105258-4FB8-FC45-B691-A00612A4A218}" sibTransId="{8B7335AD-E8E3-B540-A78E-B15B18EA174D}"/><dgm:cxn modelId="{43917434-DF30-B848-BEE2-21CD9A51C9F7}" srcId="{6B1B2AEF-22F4-AC48-8A93-AB0CB308BE29}" destId="{7EC28C01-B1CB-E740-88E0-8B1B947A90BE}" srcOrd="6" destOrd="0" parTransId="{536E123D-41B8-5943-A0C0-CBF91265352D}" sibTransId="{35F9A163-1378-3344-8B65-356AB8D3CFB8}"/><dgm:cxn modelId="{86BB203C-C5B5-FF48-879F-83F0F19934F5}" type="presOf" srcId="{10F8E38D-B283-824B-BB42-63E45FF74DA9}" destId="{7BECD734-A12F-534A-89A0-5868FE57EAFC}" srcOrd="0" destOrd="0" presId="urn:microsoft.com/office/officeart/2005/8/layout/hChevron3"/><dgm:cxn modelId="{0428DC5D-881F-B742-9C29-23BD3B0CC45F}" srcId="{6B1B2AEF-22F4-AC48-8A93-AB0CB308BE29}" destId="{7B63C8FB-3594-9F4C-AA26-6E34EF478988}" srcOrd="3" destOrd="0" parTransId="{33C868A5-0974-2443-88E7-8E0EE4F8547E}" sibTransId="{6DCD0E73-6C12-2F49-ABA4-A94461CE8E33}"/><dgm:cxn modelId="{BEE2664C-9235-C541-802D-E3F7AA7BEF79}" srcId="{6B1B2AEF-22F4-AC48-8A93-AB0CB308BE29}" destId="{29493BC4-8567-DC44-8124-D9A4E206014B}" srcOrd="5" destOrd="0" parTransId="{750DED83-2DDF-EF4B-9BDA-90028A97299D}" sibTransId="{F059D63E-6FC1-3D43-B123-5800FD425444}"/><dgm:cxn modelId="{A850D459-1BBC-3B4B-8C7E-B5F819606E9C}" type="presOf" srcId="{4AEC236B-9451-FE45-8C5E-68D1AA342D88}" destId="{9C4DA93F-6182-1C4F-B14A-DE5E65D63BCA}" srcOrd="0" destOrd="0" presId="urn:microsoft.com/office/officeart/2005/8/layout/hChevron3"/><dgm:cxn modelId="{81C14380-0E60-5C47-8602-5B33B615EB42}" type="presOf" srcId="{3AD67424-697F-3C4E-AF06-C23AA73C6735}" destId="{E52473DA-8085-644E-A894-B9D49D220693}" srcOrd="0" destOrd="0" presId="urn:microsoft.com/office/officeart/2005/8/layout/hChevron3"/><dgm:cxn modelId="{270A698C-79CC-BA4F-BA71-C01DD8069CDB}" srcId="{6B1B2AEF-22F4-AC48-8A93-AB0CB308BE29}" destId="{3AD67424-697F-3C4E-AF06-C23AA73C6735}" srcOrd="0" destOrd="0" parTransId="{94A1EA08-330E-1C4F-A5F6-B6D027255A25}" sibTransId="{B660B384-A234-FF4B-953C-B968334A83B1}"/><dgm:cxn modelId="{496521A0-C711-0544-97A4-8156C7A3CC62}" type="presOf" srcId="{6B1B2AEF-22F4-AC48-8A93-AB0CB308BE29}" destId="{5E5CA806-1D07-5F45-B976-8288ED4D0D28}" srcOrd="0" destOrd="0" presId="urn:microsoft.com/office/officeart/2005/8/layout/hChevron3"/><dgm:cxn modelId="{735FF7A0-A1B2-2B48-B7AA-8B3F6CA7AA2B}" srcId="{6B1B2AEF-22F4-AC48-8A93-AB0CB308BE29}" destId="{4AEC236B-9451-FE45-8C5E-68D1AA342D88}" srcOrd="1" destOrd="0" parTransId="{AF267801-2239-F94A-B583-C7FB27956B7F}" sibTransId="{41AD188D-17A6-8643-88D4-9938D158A470}"/><dgm:cxn modelId="{FA2FA4A2-43B7-9947-BE5A-34D5676C38A0}" type="presOf" srcId="{7B63C8FB-3594-9F4C-AA26-6E34EF478988}" destId="{9E113E60-D12D-7745-BF29-D52C962884CE}" srcOrd="0" destOrd="0" presId="urn:microsoft.com/office/officeart/2005/8/layout/hChevron3"/><dgm:cxn modelId="{8DEFA1B0-74D5-094A-85F9-28816BC6DD91}" type="presOf" srcId="{29493BC4-8567-DC44-8124-D9A4E206014B}" destId="{9E51B29C-3BED-9640-B87A-882DE8B574A5}" srcOrd="0" destOrd="0" presId="urn:microsoft.com/office/officeart/2005/8/layout/hChevron3"/><dgm:cxn modelId="{02681EC7-71CE-7543-81E5-3000B0E7F488}" type="presOf" srcId="{15C0F98F-A1BA-E545-B3AC-C70E2FD60E30}" destId="{54E784E2-E136-2242-A4D6-7739730A0D5F}" srcOrd="0" destOrd="0" presId="urn:microsoft.com/office/officeart/2005/8/layout/hChevron3"/><dgm:cxn modelId="{036E21DD-8B81-954A-912A-380B2698B141}" type="presOf" srcId="{7EC28C01-B1CB-E740-88E0-8B1B947A90BE}" destId="{EA6F2962-465F-464A-B531-E0DD672D52E8}" srcOrd="0" destOrd="0" presId="urn:microsoft.com/office/officeart/2005/8/layout/hChevron3"/><dgm:cxn modelId="{E57464E3-C512-A942-9482-554D96FBAF65}" srcId="{6B1B2AEF-22F4-AC48-8A93-AB0CB308BE29}" destId="{15C0F98F-A1BA-E545-B3AC-C70E2FD60E30}" srcOrd="2" destOrd="0" parTransId="{F34FC41A-5477-8F43-BFA0-1C6486C8F3D7}" sibTransId="{41625998-06A4-3D44-A4C7-DAB70713663D}"/><dgm:cxn modelId="{B3A31982-9C1B-3E4B-9DB3-FA11606FE083}" type="presParOf" srcId="{5E5CA806-1D07-5F45-B976-8288ED4D0D28}" destId="{E52473DA-8085-644E-A894-B9D49D220693}" srcOrd="0" destOrd="0" presId="urn:microsoft.com/office/officeart/2005/8/layout/hChevron3"/><dgm:cxn modelId="{A8E6EA2A-92ED-6045-9FCA-74775C7DDDF6}" type="presParOf" srcId="{5E5CA806-1D07-5F45-B976-8288ED4D0D28}" destId="{293B8D6C-3AE8-FD4D-9E38-D46F2D15017B}" srcOrd="1" destOrd="0" presId="urn:microsoft.com/office/officeart/2005/8/layout/hChevron3"/><dgm:cxn modelId="{42484764-79D1-5F41-B884-3E3BA2512E40}" type="presParOf" srcId="{5E5CA806-1D07-5F45-B976-8288ED4D0D28}" destId="{9C4DA93F-6182-1C4F-B14A-DE5E65D63BCA}" srcOrd="2" destOrd="0" presId="urn:microsoft.com/office/officeart/2005/8/layout/hChevron3"/><dgm:cxn modelId="{C785FC52-7692-294D-93C2-22439F8C79CB}" type="presParOf" srcId="{5E5CA806-1D07-5F45-B976-8288ED4D0D28}" destId="{B53EC07B-4AB7-0C47-9190-7F61A4B97119}" srcOrd="3" destOrd="0" presId="urn:microsoft.com/office/officeart/2005/8/layout/hChevron3"/><dgm:cxn modelId="{02277765-592A-7742-B1D0-9FEE2672DB02}" type="presParOf" srcId="{5E5CA806-1D07-5F45-B976-8288ED4D0D28}" destId="{54E784E2-E136-2242-A4D6-7739730A0D5F}" srcOrd="4" destOrd="0" presId="urn:microsoft.com/office/officeart/2005/8/layout/hChevron3"/><dgm:cxn modelId="{AFEEEA3B-A345-054F-B158-FE77374A468E}" type="presParOf" srcId="{5E5CA806-1D07-5F45-B976-8288ED4D0D28}" destId="{EB4F028F-6C69-DC4B-A30F-9B616CB88233}" srcOrd="5" destOrd="0" presId="urn:microsoft.com/office/officeart/2005/8/layout/hChevron3"/><dgm:cxn modelId="{1B3E5ACC-A544-EE4C-A0A2-FFBC5AB14ACA}" type="presParOf" srcId="{5E5CA806-1D07-5F45-B976-8288ED4D0D28}" destId="{9E113E60-D12D-7745-BF29-D52C962884CE}" srcOrd="6" destOrd="0" presId="urn:microsoft.com/office/officeart/2005/8/layout/hChevron3"/><dgm:cxn modelId="{FED613D3-5DD4-3A48-9C39-55CC431F85EA}" type="presParOf" srcId="{5E5CA806-1D07-5F45-B976-8288ED4D0D28}" destId="{5E5369F1-0642-AA42-BCEC-EF0F2E94DA01}" srcOrd="7" destOrd="0" presId="urn:microsoft.com/office/officeart/2005/8/layout/hChevron3"/><dgm:cxn modelId="{71404DBC-7094-B944-A5B8-206F44EB8057}" type="presParOf" srcId="{5E5CA806-1D07-5F45-B976-8288ED4D0D28}" destId="{7BECD734-A12F-534A-89A0-5868FE57EAFC}" srcOrd="8" destOrd="0" presId="urn:microsoft.com/office/officeart/2005/8/layout/hChevron3"/><dgm:cxn modelId="{8DB76471-9116-C448-884D-4EA35DF42251}" type="presParOf" srcId="{5E5CA806-1D07-5F45-B976-8288ED4D0D28}" destId="{F1495C49-065A-504A-8C90-355DE9B579D5}" srcOrd="9" destOrd="0" presId="urn:microsoft.com/office/officeart/2005/8/layout/hChevron3"/><dgm:cxn modelId="{C0A92B62-725C-3145-B26E-A6D70375A11B}" type="presParOf" srcId="{5E5CA806-1D07-5F45-B976-8288ED4D0D28}" destId="{9E51B29C-3BED-9640-B87A-882DE8B574A5}" srcOrd="10" destOrd="0" presId="urn:microsoft.com/office/officeart/2005/8/layout/hChevron3"/><dgm:cxn modelId="{0E3E40A1-86F9-3849-AE07-0FC8850B8906}" type="presParOf" srcId="{5E5CA806-1D07-5F45-B976-8288ED4D0D28}" destId="{CB802434-164D-2B47-A8E6-CB84BE54A879}" srcOrd="11" destOrd="0" presId="urn:microsoft.com/office/officeart/2005/8/layout/hChevron3"/><dgm:cxn modelId="{2FD01188-087A-CA40-9E99-01C53D665CBD}" type="presParOf" srcId="{5E5CA806-1D07-5F45-B976-8288ED4D0D28}" destId="{EA6F2962-465F-464A-B531-E0DD672D52E8}" srcOrd="12" destOrd="0" presId="urn:microsoft.com/office/officeart/2005/8/layout/hChevron3"/></dgm:cxnLst><dgm:bg/><dgm:whole/><dgm:extLst><a:ext uri="http://schemas.microsoft.com/office/drawing/2008/diagram"><dsp:dataModelExt xmlns:dsp="http://schemas.microsoft.com/office/drawing/2008/diagram" relId="rId7" minVer="http://schemas.openxmlformats.org/drawingml/2006/diagram"/></a:ext></dgm:extLst></dgm:dataModel>