<?xml version="1.0" encoding="UTF-8" standalone="yes"?>
<dsp:drawing xmlns:dgm="http://schemas.openxmlformats.org/drawingml/2006/diagram" xmlns:dsp="http://schemas.microsoft.com/office/drawing/2008/diagram" xmlns:a="http://schemas.openxmlformats.org/drawingml/2006/main"><dsp:spTree><dsp:nvGrpSpPr><dsp:cNvPr id="0" name=""/><dsp:cNvGrpSpPr/></dsp:nvGrpSpPr><dsp:grpSpPr/><dsp:sp modelId="{BFC56C4A-865B-1E4D-8728-4436FCAE42B5}"><dsp:nvSpPr><dsp:cNvPr id="0" name=""/><dsp:cNvSpPr/></dsp:nvSpPr><dsp:spPr><a:xfrm><a:off x="4685645" y="33164"/><a:ext cx="1111225" cy="1111225"/></a:xfrm><a:prstGeom prst="rect"><a:avLst/></a:prstGeom><a:noFill/><a:ln><a:noFill/></a:ln><a:effectLst/></dsp:spPr><dsp:style><a:lnRef idx="0"><a:scrgbClr r="0" g="0" b="0"/></a:lnRef><a:fillRef idx="0"><a:scrgbClr r="0" g="0" b="0"/></a:fillRef><a:effectRef idx="0"><a:scrgbClr r="0" g="0" b="0"/></a:effectRef><a:fontRef idx="minor"/></dsp:style><dsp:txBody><a:bodyPr spcFirstLastPara="0" vert="horz" wrap="square" lIns="15240" tIns="15240" rIns="15240" bIns="15240" numCol="1" spcCol="1270" anchor="ctr" anchorCtr="0"><a:noAutofit/></a:bodyPr><a:lstStyle/><a:p><a:pPr marL="0" lvl="0" indent="0" algn="ctr" defTabSz="533400"><a:lnSpc><a:spcPct val="90000"/></a:lnSpc><a:spcBef><a:spcPct val="0"/></a:spcBef><a:spcAft><a:spcPct val="35000"/></a:spcAft><a:buNone/></a:pPr><a:endParaRPr lang="en-US" sz="1200" kern="1200" dirty="0"/></a:p></dsp:txBody><dsp:txXfrm><a:off x="4685645" y="33164"/><a:ext cx="1111225" cy="1111225"/></dsp:txXfrm></dsp:sp><dsp:sp modelId="{AE896A5D-7005-DF43-B9CF-E7CE96E2429F}"><dsp:nvSpPr><dsp:cNvPr id="0" name=""/><dsp:cNvSpPr/></dsp:nvSpPr><dsp:spPr><a:xfrm><a:off x="2066529" y="401"/><a:ext cx="4172741" cy="4172741"/></a:xfrm><a:prstGeom prst="circularArrow"><a:avLst><a:gd name="adj1" fmla="val 5193"/><a:gd name="adj2" fmla="val 335389"/><a:gd name="adj3" fmla="val 21295377"/><a:gd name="adj4" fmla="val 19764368"/><a:gd name="adj5" fmla="val 6058"/></a:avLst></a:prstGeom><a:solidFill><a:schemeClr val="accent3"/></a:solidFill><a:ln><a:solidFill><a:schemeClr val="tx1"/></a:solidFill></a:ln><a:effectLst/></dsp:spPr><dsp:style><a:lnRef idx="0"><a:scrgbClr r="0" g="0" b="0"/></a:lnRef><a:fillRef idx="3"><a:scrgbClr r="0" g="0" b="0"/></a:fillRef><a:effectRef idx="2"><a:scrgbClr r="0" g="0" b="0"/></a:effectRef><a:fontRef idx="minor"><a:schemeClr val="lt1"/></a:fontRef></dsp:style></dsp:sp><dsp:sp modelId="{636FB31E-CB48-9645-9C82-47AAA83C1D73}"><dsp:nvSpPr><dsp:cNvPr id="0" name=""/><dsp:cNvSpPr/></dsp:nvSpPr><dsp:spPr><a:xfrm><a:off x="5358287" y="2103343"/><a:ext cx="1111225" cy="1111225"/></a:xfrm><a:prstGeom prst="rect"><a:avLst/></a:prstGeom><a:noFill/><a:ln><a:noFill/></a:ln><a:effectLst/></dsp:spPr><dsp:style><a:lnRef idx="0"><a:scrgbClr r="0" g="0" b="0"/></a:lnRef><a:fillRef idx="0"><a:scrgbClr r="0" g="0" b="0"/></a:fillRef><a:effectRef idx="0"><a:scrgbClr r="0" g="0" b="0"/></a:effectRef><a:fontRef idx="minor"/></dsp:style><dsp:txBody><a:bodyPr spcFirstLastPara="0" vert="horz" wrap="square" lIns="15240" tIns="15240" rIns="15240" bIns="15240" numCol="1" spcCol="1270" anchor="ctr" anchorCtr="0"><a:noAutofit/></a:bodyPr><a:lstStyle/><a:p><a:pPr marL="0" lvl="0" indent="0" algn="ctr" defTabSz="533400"><a:lnSpc><a:spcPct val="90000"/></a:lnSpc><a:spcBef><a:spcPct val="0"/></a:spcBef><a:spcAft><a:spcPct val="35000"/></a:spcAft><a:buNone/></a:pPr><a:endParaRPr lang="en-US" sz="1200" kern="1200"/></a:p></dsp:txBody><dsp:txXfrm><a:off x="5358287" y="2103343"/><a:ext cx="1111225" cy="1111225"/></dsp:txXfrm></dsp:sp><dsp:sp modelId="{CC12B20E-F42C-804C-873A-AACD337C0385}"><dsp:nvSpPr><dsp:cNvPr id="0" name=""/><dsp:cNvSpPr/></dsp:nvSpPr><dsp:spPr><a:xfrm><a:off x="2066529" y="401"/><a:ext cx="4172741" cy="4172741"/></a:xfrm><a:prstGeom prst="circularArrow"><a:avLst><a:gd name="adj1" fmla="val 5193"/><a:gd name="adj2" fmla="val 335389"/><a:gd name="adj3" fmla="val 4016911"/><a:gd name="adj4" fmla="val 2251401"/><a:gd name="adj5" fmla="val 6058"/></a:avLst></a:prstGeom><a:solidFill><a:schemeClr val="accent3"/></a:solidFill><a:ln><a:solidFill><a:schemeClr val="tx1"/></a:solidFill></a:ln><a:effectLst/></dsp:spPr><dsp:style><a:lnRef idx="0"><a:scrgbClr r="0" g="0" b="0"/></a:lnRef><a:fillRef idx="3"><a:scrgbClr r="0" g="0" b="0"/></a:fillRef><a:effectRef idx="2"><a:scrgbClr r="0" g="0" b="0"/></a:effectRef><a:fontRef idx="minor"><a:schemeClr val="lt1"/></a:fontRef></dsp:style></dsp:sp><dsp:sp modelId="{77575AB8-8C30-F245-AF98-E581882300FF}"><dsp:nvSpPr><dsp:cNvPr id="0" name=""/><dsp:cNvSpPr/></dsp:nvSpPr><dsp:spPr><a:xfrm><a:off x="3597287" y="3382784"/><a:ext cx="1111225" cy="1111225"/></a:xfrm><a:prstGeom prst="rect"><a:avLst/></a:prstGeom><a:noFill/><a:ln><a:noFill/></a:ln><a:effectLst/></dsp:spPr><dsp:style><a:lnRef idx="0"><a:scrgbClr r="0" g="0" b="0"/></a:lnRef><a:fillRef idx="0"><a:scrgbClr r="0" g="0" b="0"/></a:fillRef><a:effectRef idx="0"><a:scrgbClr r="0" g="0" b="0"/></a:effectRef><a:fontRef idx="minor"/></dsp:style><dsp:txBody><a:bodyPr spcFirstLastPara="0" vert="horz" wrap="square" lIns="15240" tIns="15240" rIns="15240" bIns="15240" numCol="1" spcCol="1270" anchor="ctr" anchorCtr="0"><a:noAutofit/></a:bodyPr><a:lstStyle/><a:p><a:pPr marL="0" lvl="0" indent="0" algn="ctr" defTabSz="533400"><a:lnSpc><a:spcPct val="90000"/></a:lnSpc><a:spcBef><a:spcPct val="0"/></a:spcBef><a:spcAft><a:spcPct val="35000"/></a:spcAft><a:buNone/></a:pPr><a:endParaRPr lang="en-US" sz="1200" kern="1200"/></a:p></dsp:txBody><dsp:txXfrm><a:off x="3597287" y="3382784"/><a:ext cx="1111225" cy="1111225"/></dsp:txXfrm></dsp:sp><dsp:sp modelId="{5B477DB2-382F-A347-8FEC-80F6D7332CFB}"><dsp:nvSpPr><dsp:cNvPr id="0" name=""/><dsp:cNvSpPr/></dsp:nvSpPr><dsp:spPr><a:xfrm><a:off x="2066529" y="401"/><a:ext cx="4172741" cy="4172741"/></a:xfrm><a:prstGeom prst="circularArrow"><a:avLst><a:gd name="adj1" fmla="val 5193"/><a:gd name="adj2" fmla="val 335389"/><a:gd name="adj3" fmla="val 8213210"/><a:gd name="adj4" fmla="val 6447700"/><a:gd name="adj5" fmla="val 6058"/></a:avLst></a:prstGeom><a:solidFill><a:schemeClr val="accent3"/></a:solidFill><a:ln><a:solidFill><a:schemeClr val="tx1"/></a:solidFill></a:ln><a:effectLst/></dsp:spPr><dsp:style><a:lnRef idx="0"><a:scrgbClr r="0" g="0" b="0"/></a:lnRef><a:fillRef idx="3"><a:scrgbClr r="0" g="0" b="0"/></a:fillRef><a:effectRef idx="2"><a:scrgbClr r="0" g="0" b="0"/></a:effectRef><a:fontRef idx="minor"><a:schemeClr val="lt1"/></a:fontRef></dsp:style></dsp:sp><dsp:sp modelId="{1924AA87-D401-4A41-A0A0-4704473041FC}"><dsp:nvSpPr><dsp:cNvPr id="0" name=""/><dsp:cNvSpPr/></dsp:nvSpPr><dsp:spPr><a:xfrm><a:off x="1836287" y="2103343"/><a:ext cx="1111225" cy="1111225"/></a:xfrm><a:prstGeom prst="rect"><a:avLst/></a:prstGeom><a:noFill/><a:ln><a:noFill/></a:ln><a:effectLst/></dsp:spPr><dsp:style><a:lnRef idx="0"><a:scrgbClr r="0" g="0" b="0"/></a:lnRef><a:fillRef idx="0"><a:scrgbClr r="0" g="0" b="0"/></a:fillRef><a:effectRef idx="0"><a:scrgbClr r="0" g="0" b="0"/></a:effectRef><a:fontRef idx="minor"/></dsp:style><dsp:txBody><a:bodyPr spcFirstLastPara="0" vert="horz" wrap="square" lIns="15240" tIns="15240" rIns="15240" bIns="15240" numCol="1" spcCol="1270" anchor="ctr" anchorCtr="0"><a:noAutofit/></a:bodyPr><a:lstStyle/><a:p><a:pPr marL="0" lvl="0" indent="0" algn="ctr" defTabSz="533400"><a:lnSpc><a:spcPct val="90000"/></a:lnSpc><a:spcBef><a:spcPct val="0"/></a:spcBef><a:spcAft><a:spcPct val="35000"/></a:spcAft><a:buNone/></a:pPr><a:endParaRPr lang="en-US" sz="1200" kern="1200"/></a:p></dsp:txBody><dsp:txXfrm><a:off x="1836287" y="2103343"/><a:ext cx="1111225" cy="1111225"/></dsp:txXfrm></dsp:sp><dsp:sp modelId="{972B0EE6-58C2-5743-B304-5B3D3A178C3C}"><dsp:nvSpPr><dsp:cNvPr id="0" name=""/><dsp:cNvSpPr/></dsp:nvSpPr><dsp:spPr><a:xfrm><a:off x="2066529" y="401"/><a:ext cx="4172741" cy="4172741"/></a:xfrm><a:prstGeom prst="circularArrow"><a:avLst><a:gd name="adj1" fmla="val 5193"/><a:gd name="adj2" fmla="val 335389"/><a:gd name="adj3" fmla="val 12300243"/><a:gd name="adj4" fmla="val 10769234"/><a:gd name="adj5" fmla="val 6058"/></a:avLst></a:prstGeom><a:solidFill><a:schemeClr val="accent3"/></a:solidFill><a:ln><a:solidFill><a:schemeClr val="tx1"/></a:solidFill></a:ln><a:effectLst/></dsp:spPr><dsp:style><a:lnRef idx="0"><a:scrgbClr r="0" g="0" b="0"/></a:lnRef><a:fillRef idx="3"><a:scrgbClr r="0" g="0" b="0"/></a:fillRef><a:effectRef idx="2"><a:scrgbClr r="0" g="0" b="0"/></a:effectRef><a:fontRef idx="minor"><a:schemeClr val="lt1"/></a:fontRef></dsp:style></dsp:sp><dsp:sp modelId="{A3D9EC7D-B58F-9A44-8871-383CFA6256F2}"><dsp:nvSpPr><dsp:cNvPr id="0" name=""/><dsp:cNvSpPr/></dsp:nvSpPr><dsp:spPr><a:xfrm><a:off x="2508929" y="33164"/><a:ext cx="1111225" cy="1111225"/></a:xfrm><a:prstGeom prst="rect"><a:avLst/></a:prstGeom><a:noFill/><a:ln><a:noFill/></a:ln><a:effectLst/></dsp:spPr><dsp:style><a:lnRef idx="0"><a:scrgbClr r="0" g="0" b="0"/></a:lnRef><a:fillRef idx="0"><a:scrgbClr r="0" g="0" b="0"/></a:fillRef><a:effectRef idx="0"><a:scrgbClr r="0" g="0" b="0"/></a:effectRef><a:fontRef idx="minor"/></dsp:style><dsp:txBody><a:bodyPr spcFirstLastPara="0" vert="horz" wrap="square" lIns="15240" tIns="15240" rIns="15240" bIns="15240" numCol="1" spcCol="1270" anchor="ctr" anchorCtr="0"><a:noAutofit/></a:bodyPr><a:lstStyle/><a:p><a:pPr marL="0" lvl="0" indent="0" algn="ctr" defTabSz="533400"><a:lnSpc><a:spcPct val="90000"/></a:lnSpc><a:spcBef><a:spcPct val="0"/></a:spcBef><a:spcAft><a:spcPct val="35000"/></a:spcAft><a:buNone/></a:pPr><a:endParaRPr lang="en-US" sz="1200" kern="1200"/></a:p></dsp:txBody><dsp:txXfrm><a:off x="2508929" y="33164"/><a:ext cx="1111225" cy="1111225"/></dsp:txXfrm></dsp:sp><dsp:sp modelId="{F72C8F80-53E3-8B46-93F2-97C4308E5F76}"><dsp:nvSpPr><dsp:cNvPr id="0" name=""/><dsp:cNvSpPr/></dsp:nvSpPr><dsp:spPr><a:xfrm><a:off x="2066529" y="401"/><a:ext cx="4172741" cy="4172741"/></a:xfrm><a:prstGeom prst="circularArrow"><a:avLst><a:gd name="adj1" fmla="val 5193"/><a:gd name="adj2" fmla="val 335389"/><a:gd name="adj3" fmla="val 16867893"/><a:gd name="adj4" fmla="val 15196718"/><a:gd name="adj5" fmla="val 6058"/></a:avLst></a:prstGeom><a:solidFill><a:schemeClr val="accent3"/></a:solidFill><a:ln><a:solidFill><a:schemeClr val="tx1"/></a:solidFill></a:ln><a:effectLst/></dsp:spPr><dsp:style><a:lnRef idx="0"><a:scrgbClr r="0" g="0" b="0"/></a:lnRef><a:fillRef idx="3"><a:scrgbClr r="0" g="0" b="0"/></a:fillRef><a:effectRef idx="2"><a:scrgbClr r="0" g="0" b="0"/></a:effectRef><a:fontRef idx="minor"><a:schemeClr val="lt1"/></a:fontRef></dsp:style></dsp:sp></dsp:spTree></dsp:drawing>